README.rst
setup.py
ScalPy.egg-info/PKG-INFO
ScalPy.egg-info/SOURCES.txt
ScalPy.egg-info/dependency_links.txt
ScalPy.egg-info/requires.txt
ScalPy.egg-info/top_level.txt
scalpy/__init__.py
scalpy/fluids.py
scalpy/scalar.py
scalpy/solver.py
scalpy/transfer_func.py