Metadata-Version: 1.1
Name: ScalPy
Version: 0.1.0b
Summary: a package for studying dynamics of scalar fields in cosmology.
Home-page: http://github.com/sum33it/scalpy
Author: Sumit Kumar, Abhishek Jana and Anjan A. Sen
Author-email: sumit@ctp-jamia.res.in
License: GNU GENERAL PUBLIC LICENSE v3
Keywords: scalar field dynamicscosmology
Platform: UNKNOWN
Classifier: License :: OSI Approved :: GNU General Public License v3 (GPLv3) 
Classifier: Programming Language :: Python
Classifier: Programming Language :: Python :: 2.7
Classifier: Topic :: Scientific/Engineering
Classifier: Operating System :: OS Independent
